jeffy/__init__.py
jeffy/decorators.py
jeffy/framework.py
jeffy/logger.py
jeffy/logging.py
jeffy/settings.py
jeffy/encoding/__init__.py
jeffy/encoding/bytes.py
jeffy/encoding/json.py
jeffy/handlers/__init__.py
jeffy/handlers/common.py
jeffy/handlers/rest_api.py
jeffy/handlers/s3.py
jeffy/handlers/schedule.py
jeffy/handlers/sns.py
jeffy/handlers/sqs.py
jeffy/handlers/streams.py
jeffy/sdk/__init__.py
jeffy/sdk/kinesis.py
jeffy/sdk/s3.py
jeffy/sdk/sns.py
jeffy/sdk/sqs.py
jeffy/validator/__init__.py
jeffy/validator/jsonschema.py
jeffy-1.0.0.dist-info/METADATA
jeffy-1.0.0.dist-info/WHEEL
jeffy-1.0.0.dist-info/top_level.txt
jeffy-1.0.0.dist-info/RECORD
