Metadata-Version: 2.1
Name: jeffy
Version: 1.0.0
Summary: Event and Contract Driven Serverless "Application" Framework
Home-page: https://github.com/serverless-operations/jeffy
Author: Serverless Operations
Author-email: info@serverless-operations.com
License: MIT License
Keywords: aws lambda serverless faas
Platform: UNKNOWN
Classifier: Development Status :: 1 - Planning
Classifier: Intended Audience :: Developers
Classifier: License :: OSI Approved :: MIT License
Classifier: Programming Language :: Python
Classifier: Programming Language :: Python :: 3
Requires-Dist: jsonschema
Requires-Dist: boto3
